{"sections":{"16587717545934c482":{"type":"dynamic-slideshow","disabled":true,"blocks":{"165877175437151658-0":{"type":"slide","settings":{"background_image":"shopify:\/\/shop_images\/Laurens_blog_2.jpg","title":"","text":"","color":"#ffffff","link":"","text_alignment":"center","button_one_label":"","button_one_link":"","button_one_style":"primary","button_two_label":"","button_two_link":"","button_two_style":"primary","show_overlay":false,"overlay_color":"#000000","overlay_opacity":50}}},"block_order":["165877175437151658-0"],"settings":{"enable_autoplay":false,"autoplay_duration":8,"slideshow_width":"full","slideshow_height":"small","slideshow_height_mobile":"medium","slideshow_text_below_image":true}},"main":{"type":"static-article","settings":{"featured_image_width":"full-width","show_date":true,"show_author":true,"use_share_buttons":true}},"165878228743d005e3":{"type":"dynamic-cta","disabled":true,"settings":{"buttonText":"BACK TO The Founder's Blog","url":"https:\/\/lovewellness.com\/blogs\/work-life-balance-blog","new_tab":false,"alignment":"center","width":"regular","margin_top":30,"margin_bottom":10}},"1658764926b6439f39":{"type":"dynamic-image-with-text","settings":{"section_heading":"","image":"shopify:\/\/shop_images\/quiz-header-mob_2a0837ad-b84e-4302-a3df-c65359e5dd40.png","crop":"center","desktop_height":"natural","mobile_height":"natural","desktop_image_alignment":"left","mobile_image_alignment":"top","heading":"Build Your Customized Routine in 30 Seconds","subheading":"<p>Discover which of our clean, doctor-developed products will help you eat, sleep, feel, and live better.<\/p>","highlight":"","highlight_color":"","text_alignment":"center","button_label":"TAKE THE QUIZ","button_link":"shopify:\/\/pages\/quiz"}},"1642604591f71ddfad":{"type":"dynamic-featured-collection","settings":{"title":"Shop Our Founder's Favorites Wellness Products","highlight":"","highlight_color":"","xs_margin_top":50,"xs_margin_bottom":20,"layout":"slideshow","collection":"founder-favorites","product_count":10,"cta_label":"Shop All","cta_button_style":"primary"}}},"order":["16587717545934c482","main","165878228743d005e3","1658764926b6439f39","1642604591f71ddfad"]}